YoutaZhoulidaxuePythonGdalKechengBiji/README.md
YoutaZhoulidaxuePythonGdalKechengBiji/__init__.py
YoutaZhoulidaxuePythonGdalKechengBiji/__main__.py
YoutaZhoulidaxuePythonGdalKechengBiji/file.epub
YoutaZhoulidaxuePythonGdalKechengBiji/index.html
YoutaZhoulidaxuePythonGdalKechengBiji/css/__init__.py
YoutaZhoulidaxuePythonGdalKechengBiji/css/annotations.css
YoutaZhoulidaxuePythonGdalKechengBiji/css/main.css
YoutaZhoulidaxuePythonGdalKechengBiji/css/normalize.css
YoutaZhoulidaxuePythonGdalKechengBiji/css/popup.css
YoutaZhoulidaxuePythonGdalKechengBiji/font/__init__.py
YoutaZhoulidaxuePythonGdalKechengBiji/font/fontello.eot
YoutaZhoulidaxuePythonGdalKechengBiji/font/fontello.svg
YoutaZhoulidaxuePythonGdalKechengBiji/font/fontello.ttf
YoutaZhoulidaxuePythonGdalKechengBiji/font/fontello.woff
YoutaZhoulidaxuePythonGdalKechengBiji/img/__init__.py
YoutaZhoulidaxuePythonGdalKechengBiji/img/annotator-glyph-sprite.png
YoutaZhoulidaxuePythonGdalKechengBiji/img/annotator-icon-sprite.png
YoutaZhoulidaxuePythonGdalKechengBiji/img/apple-touch-icon.png
YoutaZhoulidaxuePythonGdalKechengBiji/img/cancelfullscreen.png
YoutaZhoulidaxuePythonGdalKechengBiji/img/close.png
YoutaZhoulidaxuePythonGdalKechengBiji/img/fullscreen.png
YoutaZhoulidaxuePythonGdalKechengBiji/img/loader.gif
YoutaZhoulidaxuePythonGdalKechengBiji/img/menu-icon.png
YoutaZhoulidaxuePythonGdalKechengBiji/img/save.png
YoutaZhoulidaxuePythonGdalKechengBiji/img/saved.png
YoutaZhoulidaxuePythonGdalKechengBiji/img/settings-s.png
YoutaZhoulidaxuePythonGdalKechengBiji/img/settings.png
YoutaZhoulidaxuePythonGdalKechengBiji/img/star.png
YoutaZhoulidaxuePythonGdalKechengBiji/js/__init__.py
YoutaZhoulidaxuePythonGdalKechengBiji/js/epub.js
YoutaZhoulidaxuePythonGdalKechengBiji/js/epub.min.js
YoutaZhoulidaxuePythonGdalKechengBiji/js/epub.min.map
YoutaZhoulidaxuePythonGdalKechengBiji/js/hooks.min.js
YoutaZhoulidaxuePythonGdalKechengBiji/js/hooks.min.map
YoutaZhoulidaxuePythonGdalKechengBiji/js/reader.js
youta_zhoulidaxue_python_gdal_kecheng_biji-2024.3.5.0.dist-info/METADATA
youta_zhoulidaxue_python_gdal_kecheng_biji-2024.3.5.0.dist-info/WHEEL
youta_zhoulidaxue_python_gdal_kecheng_biji-2024.3.5.0.dist-info/entry_points.txt
youta_zhoulidaxue_python_gdal_kecheng_biji-2024.3.5.0.dist-info/top_level.txt
youta_zhoulidaxue_python_gdal_kecheng_biji-2024.3.5.0.dist-info/RECORD
